tm1637.py
raspberrypi_tm1637-1.3.7.dist-info/LICENSE.txt
raspberrypi_tm1637-1.3.7.dist-info/METADATA
raspberrypi_tm1637-1.3.7.dist-info/WHEEL
raspberrypi_tm1637-1.3.7.dist-info/top_level.txt
raspberrypi_tm1637-1.3.7.dist-info/RECORD
