Metadata-Version: 2.1
Name: raspberrypi-tm1637
Version: 1.3.7
Summary: Raspberry Pi Python port from MicroPython library for TM1637 LED driver.
Home-page: https://github.com/depklyon/raspberrypi-tm1637
Author: Mike Causer
Author-email: mcauser@gmail.com
Maintainer: Patrick Palma
Maintainer-email: patrick.depalma@gmail.com
License: MIT
Keywords: tm1637 raspberry pi seven segment led python
Classifier: Programming Language :: Python :: 3
Classifier: Development Status :: 5 - Production/Stable
Classifier: License :: OSI Approved :: MIT License
Requires-Python: >=3
License-File: LICENSE.txt
